pyrebase/__init__.py
pyrebase/pyrebase.py
sseclient/__init__.py
sseclient/sseclient.py
Pyrebase_t-1.0.28.dist-info/METADATA
Pyrebase_t-1.0.28.dist-info/WHEEL
Pyrebase_t-1.0.28.dist-info/top_level.txt
Pyrebase_t-1.0.28.dist-info/RECORD
