Metadata-Version: 1.1
Name: Pyrebase-t
Version: 1.0.28
Summary: A simple python wrapper for the Firebase API forked from https://github.com/thisbejim/Pyrebase
Home-page: https://github.com/tupio/Pyrebase/
Author: James Childs-Maidment
Author-email: UNKNOWN
License: MIT
Keywords: Firebase Wrapper
Platform: UNKNOWN
Classifier: Development Status :: 3 - Alpha
Classifier: Intended Audience :: Developers
Classifier: License :: OSI Approved :: MIT License
Classifier: Programming Language :: Python :: 3.7
